subkey-0.1.0_alpha.3.dist-info/METADATA
subkey-0.1.0_alpha.3.dist-info/WHEEL
subkey.cpython-38-x86_64-linux-gnu.so
subkey-0.1.0_alpha.3.dist-info/RECORD
